pyautocausal/__init__.py
pyautocausal/causal_methods/double_ml.py
pyautocausal/data_cleaner_interface/__init__.py
pyautocausal/data_cleaner_interface/autocleaner.py
pyautocausal/data_cleaning/__init__.py
pyautocausal/data_cleaning/base.py
pyautocausal/data_cleaning/cleaner.py
pyautocausal/data_cleaning/example_usage.py
pyautocausal/data_cleaning/hints.py
pyautocausal/data_cleaning/operations/__init__.py
pyautocausal/data_cleaning/operations/categorical_operations.py
pyautocausal/data_cleaning/operations/duplicate_operations.py
pyautocausal/data_cleaning/operations/missing_data_operations.py
pyautocausal/data_cleaning/operations/schema_operations.py
pyautocausal/data_cleaning/operations/time_operations.py
pyautocausal/data_cleaning/planner.py
pyautocausal/data_validation/README.md
pyautocausal/data_validation/__init__.py
pyautocausal/data_validation/base.py
pyautocausal/data_validation/checks/__init__.py
pyautocausal/data_validation/checks/basic_checks.py
pyautocausal/data_validation/checks/categorical_checks.py
pyautocausal/data_validation/checks/causal_checks.py
pyautocausal/data_validation/checks/missing_data_checks.py
pyautocausal/data_validation/validator_base.py
pyautocausal/orchestration/base.py
pyautocausal/orchestration/graph.py
pyautocausal/orchestration/node_state.py
pyautocausal/orchestration/nodes.py
pyautocausal/orchestration/result.py
pyautocausal/orchestration/run_context.py
pyautocausal/persistence/__init__.py
pyautocausal/persistence/local_output_handler.py
pyautocausal/persistence/notebook_decorators.py
pyautocausal/persistence/notebook_export.py
pyautocausal/persistence/notebook_runner.py
pyautocausal/persistence/output_config.py
pyautocausal/persistence/output_handler.py
pyautocausal/persistence/output_types.py
pyautocausal/persistence/parameter_mapper.py
pyautocausal/persistence/serialization.py
pyautocausal/persistence/type_inference.py
pyautocausal/persistence/visualizer.py
pyautocausal/persistence/yaml_codec.py
pyautocausal-0.1.1.dist-info/LICENSE
pyautocausal-0.1.1.dist-info/METADATA
pyautocausal-0.1.1.dist-info/WHEEL
pyautocausal-0.1.1.dist-info/RECORD
