Metadata-Version: 2.1
Name: pyautocausal
Version: 0.1.1
Summary: Automated causal inference pipelines for data scientists
Home-page: https://github.com/NickyTops23/pyautocausal
License: MIT
Keywords: causal-inference,econometrics,statistics,difference-in-differences,synthetic-control
Author: Nicholas Topousis
Author-email: nicktopousis@gmail.com
Requires-Python: >=3.10,<3.13
Classifier: Development Status :: 3 - Alpha
Classifier: Intended Audience :: Developers
Classifier: Intended Audience :: Science/Research
Classifier: License :: OSI Approved :: MIT License
Classifier: Programming Language :: Python :: 3
Classifier: Programming Language :: Python :: 3.10
Classifier: Programming Language :: Python :: 3.11
Classifier: Programming Language :: Python :: 3.12
Classifier: Topic :: Office/Business :: Financial :: Investment
Classifier: Topic :: Scientific/Engineering :: Information Analysis
Classifier: Topic :: Scientific/Engineering :: Mathematics
Requires-Dist: cloudpickle (>=3.1.1,<4.0.0)
Requires-Dist: cvxpy (>=1.1.7)
Requires-Dist: jinja2 (>=2.10)
Requires-Dist: linearmodels (>=6.1,<7.0)
Requires-Dist: matplotlib (>=2.2.3)
Requires-Dist: nbformat (>=5.10.4,<6.0.0)
Requires-Dist: networkx (>=3.4.2,<4.0.0)
Requires-Dist: numpy (>=1.17)
Requires-Dist: pandas (>=1.1.2)
Requires-Dist: pyarrow (>=18.1.0,<19.0.0)
Requires-Dist: pyyaml (>=6.0,<7.0)
Requires-Dist: scikit-learn (>=1.6.1,<2.0.0)
Requires-Dist: scipy (>=1.4.1)
Requires-Dist: statsmodels (>=0.14.1,<0.15.0)
Project-URL: Documentation, https://github.com/NickyTops23/pyautocausal/blob/main/README.md
Project-URL: Repository, https://github.com/NickyTops23/pyautocausal
